neutrosophic_pls/__init__.py
neutrosophic_pls/__main__.py
neutrosophic_pls/algebra.py
neutrosophic_pls/cli.py
neutrosophic_pls/data_idrc.py
neutrosophic_pls/data_loader.py
neutrosophic_pls/data_micromass.py
neutrosophic_pls/encoders.py
neutrosophic_pls/interactive.py
neutrosophic_pls/metrics.py
neutrosophic_pls/model.py
neutrosophic_pls/model_factory.py
neutrosophic_pls/notebook.py
neutrosophic_pls/reduction.py
neutrosophic_pls/semantic.py
neutrosophic_pls/simulate.py
neutrosophic_pls/study_config.py
neutrosophic_pls/validation.py
neutrosophic_pls/vip.py
neutrosophic_pls/fixtures/micromass_fixture.arff
neutrosophic_pls-1.0.1.dist-info/licenses/LICENSE
neutrosophic_pls-1.0.1.dist-info/METADATA
neutrosophic_pls-1.0.1.dist-info/WHEEL
neutrosophic_pls-1.0.1.dist-info/entry_points.txt
neutrosophic_pls-1.0.1.dist-info/top_level.txt
neutrosophic_pls-1.0.1.dist-info/RECORD
