Metadata-Version: 2.4
Name: neutrosophic-pls
Version: 1.0.1
Summary: Neutrosophic Partial Least Squares (N-PLS): Uncertainty-aware PLS with Truth/Indeterminacy/Falsity encoding for chemometrics and spectroscopy
Author-email: Dickson Abdul-Wahab <dabdul-wahab@live.com>, Ebenezer Aquisman Asare <aquisman1989@gmail.com>
Maintainer-email: Dickson Abdul-Wahab <dabdul-wahab@live.com>
License: MIT
Project-URL: Homepage, https://github.com/dabdul-wahab1988/neutrosophic_pls
Project-URL: Documentation, https://github.com/dabdul-wahab1988/neutrosophic_pls/blob/main/README.md
Project-URL: Repository, https://github.com/dabdul-wahab1988/neutrosophic_pls.git
Project-URL: Issues, https://github.com/dabdul-wahab1988/neutrosophic_pls/issues
Keywords: partial-least-squares,pls,neutrosophic,chemometrics,spectroscopy,nir,uncertainty-quantification,machine-learning,regression,variable-importance
Classifier: Development Status :: 4 - Beta
Classifier: Intended Audience :: Science/Research
Classifier: Intended Audience :: Developers
Classifier: License :: OSI Approved :: MIT License
Classifier: Operating System :: OS Independent
Classifier: Programming Language :: Python :: 3
Classifier: Programming Language :: Python :: 3.9
Classifier: Programming Language :: Python :: 3.10
Classifier: Programming Language :: Python :: 3.11
Classifier: Programming Language :: Python :: 3.12
Classifier: Topic :: Scientific/Engineering
Classifier: Topic :: Scientific/Engineering :: Chemistry
Classifier: Topic :: Scientific/Engineering :: Artificial Intelligence
Classifier: Topic :: Scientific/Engineering :: Information Analysis
Requires-Python: >=3.9
License-File: LICENSE
Requires-Dist: numpy>=1.21.0
Requires-Dist: scipy>=1.7.0
Requires-Dist: pandas>=1.3.0
Requires-Dist: scikit-learn>=1.0.0
Requires-Dist: matplotlib>=3.4.0
Requires-Dist: pyyaml>=6.0
Provides-Extra: dev
Requires-Dist: pytest>=7.0; extra == "dev"
Requires-Dist: pytest-cov>=4.0; extra == "dev"
Requires-Dist: hypothesis>=6.0; extra == "dev"
Requires-Dist: black>=23.0; extra == "dev"
Requires-Dist: ruff>=0.1.0; extra == "dev"
Requires-Dist: mypy>=1.0; extra == "dev"
Provides-Extra: docs
Requires-Dist: sphinx>=6.0; extra == "docs"
Requires-Dist: sphinx-rtd-theme>=1.0; extra == "docs"
Requires-Dist: myst-parser>=2.0; extra == "docs"
Provides-Extra: all
Requires-Dist: neutrosophic-pls[dev,docs]; extra == "all"
Dynamic: license-file
